py_ai_toolbox/__init__.py
py_ai_toolbox/hf_download.py
py_ai_toolbox-0.0.14.dist-info/entry_points.txt
py_ai_toolbox-0.0.14.dist-info/LICENSE
py_ai_toolbox-0.0.14.dist-info/WHEEL
py_ai_toolbox-0.0.14.dist-info/METADATA
py_ai_toolbox-0.0.14.dist-info/RECORD
