Metadata-Version: 2.1
Name: py_ai_toolbox
Version: 0.0.14
Summary: This module provide a toolbox for ai dev.
Classifier: License :: OSI Approved :: MIT License
